ka_app_cfg/__init__.py
ka_app_cfg/__version__.py
ka_app_cfg/do.py
ka_app_cfg/parms.py
ka_app_cfg/py.typed
ka_app_cfg/setup.py
ka_app_cfg/task.py
ka_app_cfg/cfg/log.std.yml
ka_app_cfg/cfg/log.usr.yml
ka_app_cfg-5.0.0.250623.dist-info/licenses/LICENSE.txt
ka_app_cfg-5.0.0.250623.dist-info/METADATA
ka_app_cfg-5.0.0.250623.dist-info/WHEEL
ka_app_cfg-5.0.0.250623.dist-info/entry_points.txt
ka_app_cfg-5.0.0.250623.dist-info/top_level.txt
ka_app_cfg-5.0.0.250623.dist-info/RECORD
